CR-Tracker/Testing3.ipynb
CR-Tracker/__init__.py
CR-Tracker/main.py
CR-Tracker/main_ws.py
CR-Tracker/main_ws_only.py
CR-Tracker/testing4.ipynb
CR-Tracker/testing5.ipynb
CR-Tracker/__pycache__/main_ws.cpython-39.pyc
CR-Tracker/__pycache__/main_ws_only.cpython-39.pyc
cr_tracker/__init__.py
cr_tracker/main.py
cr_tracker-0.23.0.dist-info/METADATA
cr_tracker-0.23.0.dist-info/WHEEL
cr_tracker-0.23.0.dist-info/top_level.txt
cr_tracker-0.23.0.dist-info/RECORD
