Metadata-Version: 2.1
Name: cr-tracker
Version: 0.23.0
Summary: A tool to track your TFSA Contribution Room from Questrade and Wealthsimple
Home-page: https://github.com/rodnyf/CR-Tracker
Author: RF
Author-email: me@gmail.com
License: MIT
Project-URL: Source Code, https://github.com/rodnyf/CR-Tracker
Classifier: Development Status :: 3 - Alpha
Requires-Dist: questrade-api
Requires-Dist: pandas
Requires-Dist: numpy
Requires-Dist: wsimple
